sefaria_cli/__init__.py
sefaria_cli/__main__.py
sefaria_cli/cli.py
sefaria_cli-0.1.0.dist-info/licenses/LICENSE
sefaria_cli-0.1.0.dist-info/METADATA
sefaria_cli-0.1.0.dist-info/WHEEL
sefaria_cli-0.1.0.dist-info/entry_points.txt
sefaria_cli-0.1.0.dist-info/top_level.txt
sefaria_cli-0.1.0.dist-info/RECORD
