Metadata-Version: 2.4
Name: sefaria-cli
Version: 0.1.0
Summary: Command-line browser for Sefaria texts (Heb/Eng, fuzzy search, categories).
Author: Luke Jamison
License: MIT
Project-URL: Homepage, https://github.com/yourusername/sefaria-cli
Project-URL: Issues, https://github.com/yourusername/sefaria-cli/issues
Keywords: sefaria,jewish-texts,cli
Classifier: Programming Language :: Python :: 3
Classifier: License :: OSI Approved :: MIT License
Classifier: Environment :: Console
Classifier: Operating System :: MacOS
Classifier: Topic :: Text Processing :: General
Requires-Python: >=3.9
License-File: LICENSE
Requires-Dist: requests>=2.31
Requires-Dist: rich>=13.7
Requires-Dist: rapidfuzz>=3.9
Requires-Dist: charset-normalizer>=3.3
Dynamic: license-file
